physio/__init__.py
physio/cardio_respiratory_synchronization.py
physio/cyclic_deformation.py
physio/ecg.py
physio/parameters.py
physio/plotting.py
physio/preprocess.py
physio/reader.py
physio/resphrv.py
physio/respiration.py
physio/tools.py
physio-0.3.0.dist-info/licenses/LICENSE
physio-0.3.0.dist-info/METADATA
physio-0.3.0.dist-info/WHEEL
physio-0.3.0.dist-info/top_level.txt
physio-0.3.0.dist-info/RECORD
