Metadata-Version: 2.4
Name: physio
Version: 0.3.0
Summary: Simple python toolbox to analyse physio signals (respi and ECG)
Author-email: Samuel Garcia <sam.garcia.die@gmail.com>
Project-URL: homepage, https://physio.readthedocs.io
Project-URL: repository, https://github.com/samuelgarcia/physio
Classifier: Programming Language :: Python :: 3 :: Only
Classifier: License :: OSI Approved :: MIT License
Classifier: Intended Audience :: Science/Research
Classifier: Operating System :: POSIX :: Linux
Classifier: Operating System :: Microsoft :: Windows
Classifier: Operating System :: MacOS
Classifier: Operating System :: OS Independent
Requires-Python: <4.0,>=3.9
License-File: LICENSE
Requires-Dist: numpy
Requires-Dist: scipy
Requires-Dist: pandas
Requires-Dist: neo
Requires-Dist: tqdm
Provides-Extra: test
Requires-Dist: pytest; extra == "test"
Requires-Dist: matplotlib; extra == "test"
Provides-Extra: docs
Requires-Dist: matplotlib; extra == "docs"
Requires-Dist: sphinx-gallery; extra == "docs"
Requires-Dist: sphinx_rtd_theme; extra == "docs"
Requires-Dist: numpydoc; extra == "docs"
Dynamic: license-file
